telegram_notifier/__init__.py
telegram_notifier/interceptors.py
telegram_notifier/serve.py
telegram_notifier/tg_notifier.py
telegram_notifier/tg_notifier_healthcheck.py
telegram_notifier/clients/__init__.py
telegram_notifier/clients/client.py
telegram_notifier/clients/health_client.py
telegram_notifier/clients/notifier_client.py
telegram_notifier/notifier_utils/__init__.py
telegram_notifier/notifier_utils/config.py
telegram_notifier/notifier_utils/set_logger.py
telegram_notifier/notifier_utils/pb/__init__.py
telegram_notifier/notifier_utils/pb/notifier_pb2.py
telegram_notifier/notifier_utils/pb/notifier_pb2.pyi
telegram_notifier/notifier_utils/pb/notifier_pb2_grpc.py
telegram_notifier/services/__init__.py
telegram_notifier/services/notifier_service.py
telegram_grpc_dispatch-0.1.0.dist-info/METADATA
telegram_grpc_dispatch-0.1.0.dist-info/WHEEL
telegram_grpc_dispatch-0.1.0.dist-info/entry_points.txt
telegram_grpc_dispatch-0.1.0.dist-info/top_level.txt
telegram_grpc_dispatch-0.1.0.dist-info/RECORD
