Metadata-Version: 2.4
Name: telegram-grpc-dispatch
Version: 0.1.0
Requires-Python: >=3.12
Requires-Dist: elastic-apm
Requires-Dist: grpcio
Requires-Dist: grpcio-health-checking
Requires-Dist: grpcio-tools
Requires-Dist: protobuf
Requires-Dist: requests
